{"21-350":["PL","21-350","Rogo\u017aniczka","Lublin","75","Powiat bialski","0601","Mi\u0119dzyrzec Podlaski","060110","52.0297","22.885","6"],"21-500":["PL","21-500","Bia\u0142a Podlaska","Lublin","75","Bia\u0142a Podlaska","0661","Bia\u0142a Podlaska","066101","52.0277","23.1215","6"],"21-504":["PL","21-504","Rokitno (Kolonia)","Lublin","75","Powiat bialski","0601","Gmina Rokitno","060112","52.1261","23.3134","6"],"21-505":["PL","21-505","Bubel-Granna","Lublin","75","Powiat bialski","0601","Gmina Jan\u00f3w Podlaski","060105","52.2331","23.1626","6"],"21-509":["PL","21-509","El\u017cbiecin","Lublin","75","Powiat bialski","0601","Kode\u0144","060106","51.9256","23.5972","6"],"21-512":["PL","21-512","Koczuk\u00f3wka","Lublin","75","Powiat bialski","0601","Zalesie","060119","52.0704","23.3328","6"],"21-515":["PL","21-515","Krzywow\u00f3lka-Kolonia","Lublin","75","Powiat bialski","0601","Gmina S\u0142awatycze","060114","51.8103","23.5026","6"],"21-518":["PL","21-518","Pogorzelec","Lublin","75","Powiat bialski","0601","Gmina Sosn\u00f3wka","060115","51.6945","23.3419","6"],"21-523":["PL","21-523","W\u00f3lka Zab\u0142ocka-Kolonia","Lublin","75","Powiat bialski","0601","Gmina Tuczna","060117","51.8549","23.5121","6"],"21-530":["PL","21-530","Ortel Kr\u00f3lewski Drugi","Lublin","75","Powiat bialski","0601","Gmina Piszczac","060111","51.9492","23.2514","6"],"21-532":["PL","21-532","Jusaki-Zarzeka","Lublin","75","Powiat bialski","0601","Gmina \u0141omazy","060109","51.8759","23.1807","6"],"21-533":["PL","21-533","Musiej\u00f3wka","Lublin","75","Powiat bialski","0601","Rossosz","060113","51.8838","23.0676","6"],"21-540":["PL","21-540","Kobylany","Lublin","75","Powiat bialski","0601","Terespol","060116","52.0459","23.5627","6"],"21-542":["PL","21-542","Nowa Bordzi\u0142\u00f3wka","Lublin","75","Powiat bialski","0601","Le\u015bna Podlaska","060108","52.1247","23.0205","6"],"21-543":["PL","21-543","Konstantyn\u00f3w-Kolonia","Lublin","75","Powiat bialski","0601","Konstantyn\u00f3w","060107","52.2157","23.0986","6"],"21-550":["PL","21-550","Kuzawka","Lublin","75","Powiat bialski","0601","Terespol","060116","52.1098","23.5439","6"],"21-560":["PL","21-560","Rudniki","Lublin","75","Powiat bialski","0601","Mi\u0119dzyrzec Podlaski","060110","51.9992","22.8404","6"],"21-570":["PL","21-570","W\u00f3lka \u0141\u00f3zecka","Lublin","75","Powiat bialski","0601","Drel\u00f3w","060104","51.8694","22.8188","6"],"21-580":["PL","21-580","Ma\u0142gorzacin","Lublin","75","Powiat bialski","0601","Wisznice","060118","51.7883","23.2675","6"],"21-060":["PL","21-060","Boniewo","Lublin","75","Powiat krasnostawski","0606","Gmina Fajs\u0142awice","060602","51.1086","22.941","6"],"21-100":["PL","21-100","Wincent\u00f3w","Lublin","75","Powiat lubartowski","0608","Lubart\u00f3w","060807","51.4819","22.5873","6"],"21-101":["PL","21-101","\u0141ucka-Kolonia","Lublin","75","Powiat lubartowski","0608","Lubart\u00f3w","060807","51.4228","22.6402",""],"21-102":["PL","21-102","Babczyzna","Lublin","75","Powiat lubartowski","0608","Gmina Ostr\u00f3wek","060811","51.6444","22.553","6"],"21-103":["PL","21-103","Lubart\u00f3w","Lublin","75","Powiat lubartowski","0608","Lubart\u00f3w","060801","51.4802","22.6001","6"],"21-104":["PL","21-104","G\u00f3rka Lubartowska","Lublin","75","Powiat lubartowski","0608","Gmina Nied\u017awiada","060809","51.5183","22.6414","6"],"21-107":["PL","21-107","Wola Sernicka-Kolonia","Lublin","75","Powiat lubartowski","0608","Gmina Serniki","060812","51.4447","22.7156","6"],"21-108":["PL","21-108","Lubart\u00f3w","Lublin","75","Powiat lubartowski","0608","Lubart\u00f3w","060801","51.4525","22.6102","4"],"21-109":["PL","21-109","Orzech\u00f3w-Kolonia","Lublin","75","Powiat lubartowski","0608","Gmina U\u015bcim\u00f3w","060813","51.4878","22.9951","6"],"21-110":["PL","21-110","Kazn\u00f3w-Kolonia","Lublin","75","Powiat lubartowski","0608","Gmina Ostr\u00f3w Lubelski","060810","51.4876","22.777","6"],"21-115":["PL","21-115","Bia\u0142obrzegi","Lublin","75","Powiat lubartowski","0608","Gmina Kock","060806","51.6376","22.3806","6"],"21-132":["PL","21-132","Nowy Skrob\u00f3w","Lublin","75","Powiat lubartowski","0608","Kamionka","060805","51.4833","22.5073","6"],"21-136":["PL","21-136","Baran","Lublin","75","Powiat lubartowski","0608","Gmina Firlej","060803","51.5358","22.4866","6"],"21-140":["PL","21-140","Go\u0142\u0105b-Kolonia","Lublin","75","Powiat lubartowski","0608","Mich\u00f3w","060808","51.4923","22.3723","6"],"21-143":["PL","21-143","Wielkie","Lublin","75","Powiat lubartowski","0608","Abram\u00f3w","060802","51.4598","22.2769","6"],"21-146":["PL","21-146","Skrawki","Lublin","75","Powiat lubartowski","0608","Gmina Jeziorzany","060804","51.6295","22.3317","6"],"21-150":["PL","21-150","Talczyn","Lublin","75","Powiat lubartowski","0608","Gmina Kock","060806","51.6916","22.4163","6"],"21-002":["PL","21-002","Panie\u0144szczyzna","Lublin","75","Powiat lubelski","0609","Jastk\u00f3w","060907","51.2991","22.4411","6"],"21-003":["PL","21-003","Ludwin\u00f3w","Lublin","75","Powiat lubelski","0609","Gmina Niemce","060911","51.3254","22.6203","6"],"21-008":["PL","21-008","Tomaszowice-Kolonia","Lublin","75","Powiat lubelski","0609","Jastk\u00f3w","060907","51.2742","22.3672","6"],"21-025":["PL","21-025","Stoczek-Kolonia","Lublin","75","Powiat lubelski","0609","Gmina Niemce","060911","51.341","22.5194","6"],"21-030":["PL","21-030","Motycz-J\u00f3zefin","Lublin","75","Powiat lubelski","0609","Konopnica","060908","51.2535","22.4051","6"],"21-040":["PL","21-040","Kr\u0119piec","Lublin","75","Powiat \u015bwidnicki","0617","Gmina Me\u0142giew","061702","51.2054","22.7116","6"],"21-050":["PL","21-050","Bystrzejowice Trzecie","Lublin","75","Powiat \u015bwidnicki","0617","Gmina Piaski","061703","51.1436","22.7061","6"],"21-080":["PL","21-080","Piotrowice-Kolonia","Lublin","75","Powiat lubelski","0609","Garb\u00f3w","060904","51.3563","22.4164","6"],"21-010":["PL","21-010","\u0141uszcz\u00f3w-Kolonia","Lublin","75","Powiat \u0142\u0119czy\u0144ski","0610","Gmina \u0141\u0119czna","061003","51.2924","22.7862","6"],"21-011":["PL","21-011","\u0141\u0119czna","Lublin","75","Powiat \u0142\u0119czy\u0144ski","0610","Gmina \u0141\u0119czna","061003","51.2888","22.8845","6"],"21-013":["PL","21-013","Nadrybie-Dw\u00f3r","Lublin","75","Powiat \u0142\u0119czy\u0144ski","0610","Gmina Puchacz\u00f3w","061005","51.3397","23.0582","6"],"21-017":["PL","21-017","\u0141\u0119czna","Lublin","75","Powiat \u0142\u0119czy\u0144ski","0610","Gmina \u0141\u0119czna","061003","51.2908","22.8887","6"],"21-020":["PL","21-020","Cyganka","Lublin","75","Powiat \u0142\u0119czy\u0144ski","0610","Gmina Milej\u00f3w","061004","51.187","22.8872","6"],"21-070":["PL","21-070","W\u00f3lka Nadrybska","Lublin","75","Powiat \u0142\u0119czy\u0144ski","0610","Gmina Cyc\u00f3w","061001","51.3592","23.076","6"],"21-075":["PL","21-075","Stary Radzic","Lublin","75","Powiat \u0142\u0119czy\u0144ski","0610","Ludwin","061002","51.3723","22.8259","6"],"21-077":["PL","21-077","Stawek","Lublin","75","Powiat \u0142\u0119czy\u0144ski","0610","Gmina Spiczyn","061006","51.3202","22.762","6"],"21-400":["PL","21-400","Jata","Lublin","75","Powiat \u0142ukowski","0611","\u0141uk\u00f3w","061105","51.9427","22.2301","6"],"21-404":["PL","21-404","Trzebiesz\u00f3w Pierwszy","Lublin","75","Powiat \u0142ukowski","0611","Gmina Trzebiesz\u00f3w","061109","51.9807","22.5266","6"],"21-411":["PL","21-411","Burzec","Lublin","75","Powiat \u0142ukowski","0611","Gmina Wojcieszk\u00f3w","061110","51.7866","22.2624","6"],"21-412":["PL","21-412","Kalinowy D\u00f3\u0142","Lublin","75","Powiat \u0142ukowski","0611","Adam\u00f3w","061103","51.6655","22.1827","6"],"21-413":["PL","21-413","Bielany Du\u017ce","Lublin","75","Powiat \u0142ukowski","0611","Gmina Serokomla","061106","51.7103","22.2879","6"],"21-421":["PL","21-421","Stara G\u0105ska","Lublin","75","Powiat \u0142ukowski","0611","Gmina Stanin","061107","51.8312","22.2359","6"],"21-422":["PL","21-422","Stanin","Lublin","75","Powiat \u0142ukowski","0611","Gmina Stanin","061107","51.8733","22.2003","6"],"21-426":["PL","21-426","Grud\u017a","Lublin","75","Powiat \u0142ukowski","0611","Gmina Wola Mys\u0142owska","061111","51.8792","22.0348","6"],"21-450":["PL","21-450","Jamielnik-Kolonia","Lublin","75","Powiat \u0142ukowski","0611","Stoczek \u0141ukowski","061108","51.9459","22.0562","6"],"21-470":["PL","21-470","Orle Gniazdo","Lublin","75","Powiat \u0142ukowski","0611","Gmina Krzywda","061104","51.772","22.1984","6"],"21-480":["PL","21-480","Wola Okrzejska","Lublin","75","Powiat \u0142ukowski","0611","Gmina Krzywda","061104","51.7471","22.1371","6"],"21-481":["PL","21-481","Wola Gu\u0142owska","Lublin","75","Powiat \u0142ukowski","0611","Adam\u00f3w","061103","51.6983","22.2116","6"],"21-200":["PL","21-200","Micha\u0142\u00f3wka","Lublin","75","Powiat parczewski","0613","Gmina Parczew","061304","51.6302","22.9575","6"],"21-205":["PL","21-205","Holendernia","Lublin","75","Powiat parczewski","0613","Gmina Jab\u0142o\u0144","061302","51.6613","23.0714","6"],"21-210":["PL","21-210","Okalew","Lublin","75","Powiat parczewski","0613","Milan\u00f3w","061303","51.689","22.7975","6"],"21-211":["PL","21-211","Krzywowierzba-Kolonia","Lublin","75","Powiat parczewski","0613","Gmina D\u0119bowa K\u0142oda","061301","51.5887","23.1684","6"],"21-220":["PL","21-220","Ostrowik","Lublin","75","Powiat parczewski","0613","Gmina Siemie\u0144","061306","51.6369","22.7995","6"],"21-222":["PL","21-222","Nowe Mosty","Lublin","75","Powiat parczewski","0613","Gmina Podedw\u00f3rze","061305","51.6664","23.284","6"],"21-230":["PL","21-230","Lublin","Lublin","75","Lublin","0663","Lublin","066301","51.259","22.615","6"],"21-300":["PL","21-300","Bedlno Radzy\u0144skie","Lublin","75","Powiat radzy\u0144ski","0615","Radzy\u0144 Podlaski","061506","51.8238","22.6719","6"],"21-302":["PL","21-302","\u017bakowola Radzy\u0144ska","Lublin","75","Powiat radzy\u0144ski","0615","K\u0105kolewnica Wschodnia","061504","51.8694","22.6981","6"],"21-306":["PL","21-306","Wygnan\u00f3w","Lublin","75","Powiat radzy\u0144ski","0615","Czemierniki","061503","51.659","22.6329","6"],"21-307":["PL","21-307","Kl\u0119b\u00f3w","Lublin","75","Powiat radzy\u0144ski","0615","Gmina Ulan-Majorat","061507","51.8423","22.4537","6"],"21-310":["PL","21-310","Suchowola Kolonia","Lublin","75","Powiat radzy\u0144ski","0615","Gmina Wohy\u0144","061508","51.7064","22.7747","6"],"21-311":["PL","21-311","\u017bulinki","Lublin","75","Powiat radzy\u0144ski","0615","Gmina Komar\u00f3wka Podlaska","061505","51.8388","22.9444","6"],"21-345":["PL","21-345","Maruszewiec","Lublin","75","Powiat radzy\u0144ski","0615","Gmina Borki","061502","51.6971","22.5456","6"],"21-007":["PL","21-007","Piotr\u00f3wek Pierwszy","Lublin","75","Powiat \u015bwidnicki","0617","Gmina Me\u0142giew","061702","51.2554","22.8428","6"],"21-044":["PL","21-044","Stru\u017ca","Lublin","75","Powiat \u015bwidnicki","0617","Gmina Trawniki","061705","51.1518","22.9134","6"],"21-047":["PL","21-047","\u015awidnik","Lublin","75","Powiat \u015bwidnicki","0617","\u015awidnik","061701","51.2143","22.6939","6"],"21-065":["PL","21-065","Stryjno Drugie","Lublin","75","Powiat \u015bwidnicki","0617","Gmina Rybczewice","061704","51.0564","22.809","6"],"21-152":["PL","21-152","Lublin","Lublin","75","Lublin","0663","Lublin","066301","51.2784","22.5776","6"],"21-660":["PL","21-660","Jedli\u0144sk","Mazovia","78","Powiat radomski","1425","Jedli\u0144sk","142505","51.5168","21.1258","4"],"21-666":["PL","21-666","Jedlanka","Mazovia","78","Powiat radomski","1425","Jedli\u0144sk","142505","51.5433","21.0864","4"]}