{"27-300":["PL","27-300","Ma\u0142gorzacin","Mazovia","78","Powiat lipski","1409","Gmina Lipsko","140903","51.1601","21.5947",""],"27-310":["PL","27-310","Pasieki","Mazovia","78","Powiat lipski","1409","Gmina Ciepiel\u00f3w","140902","51.2033","21.4447",""],"27-312":["PL","27-312","Siekierka Nowa","Mazovia","78","Powiat lipski","1409","Gmina Chotcza","140901","51.2916","21.6775",""],"27-320":["PL","27-320","S\u0142uszczyn","Mazovia","78","Powiat lipski","1409","Gmina Solec nad Wis\u0142\u0105","140906","51.1019","21.6787",""],"27-330":["PL","27-330","Paw\u0142owice","Mazovia","78","Powiat lipski","1409","Gmina Solec nad Wis\u0142\u0105","140906","51.0702","21.7464",""],"27-350":["PL","27-350","Wierzchowiska Pierwsze","Mazovia","78","Powiat lipski","1409","Sienno","140905","51.1536","21.5242",""],"27-353":["PL","27-353","Borcuchy","Mazovia","78","Powiat lipski","1409","Gmina Rzeczni\u00f3w","140904","51.0992","21.3294",""],"27-100":["PL","27-100","Gaj\u00f3wka Antoni\u00f3w","Mazovia","78","Powiat radomski","1425","Gmina I\u0142\u017ca","142503","51.2016","21.3522",""],"27-304":["PL","27-304","Brzyska Wola","Subcarpathian Voivodeship","80","Powiat le\u017cajski","1808","Gmina Kury\u0142\u00f3wka","180803","50.3265","22.5739",""],"27-420":["PL","27-420","W\u00f3lka Bodzechowska","\u015awi\u0119tokrzyskie","84","Powiat ostrowiecki","2607","Gmina Bodzech\u00f3w","260703","50.9258","21.4519",""],"27-203":["PL","27-203","Gniewczyna Tryniecka","Subcarpathian Voivodeship","80","Powiat przeworski","1814","Gmina Try\u0144cza","181408","50.1188","22.5194",""],"27-500":["PL","27-500","Rosochy","\u015awi\u0119tokrzyskie","84","Powiat opatowski","2606","Gmina Opat\u00f3w","260604","50.8276","21.4858",""],"27-501":["PL","27-501","Opat\u00f3w","\u015awi\u0119tokrzyskie","84","Powiat opatowski","2606","Gmina Opat\u00f3w","260604","50.8005","21.4281",""],"27-515":["PL","27-515","Kolonia Kostusin","\u015awi\u0119tokrzyskie","84","Powiat opatowski","2606","Tar\u0142\u00f3w","260607","51.0626","21.6649",""],"27-530":["PL","27-530","Jankowice","\u015awi\u0119tokrzyskie","84","Powiat opatowski","2606","O\u017car\u00f3w","260605","50.8444","21.6805",""],"27-532":["PL","27-532","Or\u0142owiny","\u015awi\u0119tokrzyskie","84","Powiat opatowski","2606","Wojciechowice","260608","50.8234","21.5496",""],"27-540":["PL","27-540","Adam\u00f3w","\u015awi\u0119tokrzyskie","84","Powiat opatowski","2606","Gmina Lipnik","260603","50.7777","21.5247",""],"27-545":["PL","27-545","Stara Wie\u015b","\u015awi\u0119tokrzyskie","84","Powiat opatowski","2606","Gmina Lipnik","260603","50.7428","21.4011",""],"27-552":["PL","27-552","Piskrzyn","\u015awi\u0119tokrzyskie","84","Powiat opatowski","2606","Gmina Ba\u0107kowice","260601","50.7694","21.2703",""],"27-570":["PL","27-570","Dziewi\u0105tle","\u015awi\u0119tokrzyskie","84","Powiat opatowski","2606","Gmina Iwaniska","260602","50.6968","21.2046",""],"27-580":["PL","27-580","Ruszk\u00f3w","\u015awi\u0119tokrzyskie","84","Powiat opatowski","2606","Sadowie","260606","50.8587","21.3519",""],"27-630":["PL","27-630","Dziur\u00f3w","\u015awi\u0119tokrzyskie","84","Powiat sandomierski","2609","Gmina Zawichost","260909","50.8104","21.7961",""],"27-640":["PL","27-640","U\u0142anowice","\u015awi\u0119tokrzyskie","84","Powiat sandomierski","2609","Klimont\u00f3w","260903","50.6626","21.3729",""],"27-641":["PL","27-641","Malice","\u015awi\u0119tokrzyskie","84","Powiat sandomierski","2609","Gmina Obraz\u00f3w","260906","50.6783","21.6548",""],"27-400":["PL","27-400","Stara D\u0119bowa Wola","\u015awi\u0119tokrzyskie","84","Powiat ostrowiecki","2607","Gmina Bodzech\u00f3w","260703","50.9999","21.4287",""],"27-415":["PL","27-415","Kolonia Piaski","\u015awi\u0119tokrzyskie","84","Powiat ostrowiecki","2607","Gmina Kun\u00f3w","260705","50.9762","21.2831",""],"27-423":["PL","27-423","W\u00f3lka Ba\u0142towska-Kolonia","\u015awi\u0119tokrzyskie","84","Powiat ostrowiecki","2607","Gmina Ba\u0142t\u00f3w","260702","51.0363","21.5435",""],"27-425":["PL","27-425","Boleszyn-Kolonie","\u015awi\u0119tokrzyskie","84","Powiat ostrowiecki","2607","Wa\u015bni\u00f3w","260706","50.9249","21.185",""],"27-440":["PL","27-440","Przeuszyn","\u015awi\u0119tokrzyskie","84","Powiat ostrowiecki","2607","\u0106miel\u00f3w","260704","50.8343","21.5015",""],"27-600":["PL","27-600","Koprzywnica","\u015awi\u0119tokrzyskie","84","Powiat sandomierski","2609","Gmina Koprzywnica","260904","50.5922","21.5897",""],"27-612":["PL","27-612","Tu\u0142kowice","\u015awi\u0119tokrzyskie","84","Powiat sandomierski","2609","Gmina Wilczyce","260908","50.7427","21.6252",""],"27-620":["PL","27-620","Rzeczyca Sucha","\u015awi\u0119tokrzyskie","84","Powiat sandomierski","2609","Gmina Dwikozy","260902","50.7175","21.7534",""],"27-650":["PL","27-650","Andruszkowice","\u015awi\u0119tokrzyskie","84","Powiat sandomierski","2609","Gmina Samborzec","260907","50.6683","21.7037",""],"27-660":["PL","27-660","B\u0142onie","\u015awi\u0119tokrzyskie","84","Powiat sandomierski","2609","Gmina Koprzywnica","260904","50.5928","21.6106",""],"27-670":["PL","27-670","Wnor\u00f3w","\u015awi\u0119tokrzyskie","84","Powiat sandomierski","2609","Gmina \u0141oni\u00f3w","260905","50.5666","21.4904",""],"27-200":["PL","27-200","Starachowice","\u015awi\u0119tokrzyskie","84","Powiat starachowicki","2611","Starachowice","261101","51.0418","21.0721",""],"27-215":["PL","27-215","Rataje","\u015awi\u0119tokrzyskie","84","Powiat starachowicki","2611","Gmina W\u0105chock","261105","51.0588","21.0106",""],"27-220":["PL","27-220","Jagodne","\u015awi\u0119tokrzyskie","84","Powiat starachowicki","2611","Gmina Mirzec","261103","51.1426","20.9741",""],"27-225":["PL","27-225","Brogowiec","\u015awi\u0119tokrzyskie","84","Powiat starachowicki","2611","Paw\u0142\u00f3w","261104","50.9732","21.0131",""],"27-230":["PL","27-230","Adam\u00f3w","\u015awi\u0119tokrzyskie","84","Powiat starachowicki","2611","Brody","261102","51.022","21.1521",""],"27-231":["PL","27-231","Brody","\u015awi\u0119tokrzyskie","84","Powiat starachowicki","2611","Brody","261102","51.0178","21.2004",""],"27-233":["PL","27-233","Styk\u00f3w","\u015awi\u0119tokrzyskie","84","Powiat starachowicki","2611","Brody","261102","50.9997","21.1522",""]}