{"77-100":["PL","77-100","D\u0105bie","Pomerania","82","Powiat bytowski","2201","Byt\u00f3w","220102","54.2003","17.4861",""],"77-114":["PL","77-114","Zbys\u0142aw","Pomerania","82","Powiat bytowski","2201","Byt\u00f3w","220102","54.2402","17.4811",""],"77-115":["PL","77-115","No\u017cyno","Pomerania","82","Powiat bytowski","2201","Gmina Czarna D\u0105br\u00f3wka","220103","54.3169","17.4925","4"],"77-116":["PL","77-116","Rokiciny","Pomerania","82","Powiat bytowski","2201","Gmina Czarna D\u0105br\u00f3wka","220103","54.3402","17.7235",""],"77-121":["PL","77-121","Pomyski M\u0142yn","Pomerania","82","Powiat bytowski","2201","Byt\u00f3w","220102","54.2033","17.5593",""],"77-122":["PL","77-122","Jasie\u0144","Pomerania","82","Powiat bytowski","2201","Gmina Czarna D\u0105br\u00f3wka","220103","54.2865","17.6279","4"],"77-123":["PL","77-123","Rokity","Pomerania","82","Powiat bytowski","2201","Gmina Czarna D\u0105br\u00f3wka","220103","54.3362","17.6844","4"],"77-124":["PL","77-124","Bawernica","Pomerania","82","Powiat bytowski","2201","Gmina Parchowo","220107","54.2846","17.6996",""],"77-125":["PL","77-125","P\u00f3\u0142czno","Pomerania","82","Powiat bytowski","2201","Studzienice","220108","54.1487","17.6408",""],"77-127":["PL","77-127","Wygoda","Pomerania","82","Powiat bytowski","2201","Gmina Parchowo","220107","54.1396","17.677","4"],"77-130":["PL","77-130","Jaranty","Pomerania","82","Powiat chojnicki","2202","Konarzyny","220205","53.9327","17.3622","4"],"77-131":["PL","77-131","Rekowo","Pomerania","82","Powiat bytowski","2201","Byt\u00f3w","220102","54.085","17.4368",""],"77-132":["PL","77-132","Niezabyszewo","Pomerania","82","Powiat bytowski","2201","Byt\u00f3w","220102","54.1357","17.4256","4"],"77-133":["PL","77-133","So\u015bnica","Pomerania","82","Powiat bytowski","2201","Tuchomie","220110","54.1084","17.3132",""],"77-134":["PL","77-134","Trzebiatkowa","Pomerania","82","Powiat bytowski","2201","Tuchomie","220110","54.0674","17.2936","4"],"77-135":["PL","77-135","Popowice","Pomerania","82","Powiat bytowski","2201","Miastko","220106","54.0714","17.1892",""],"77-138":["PL","77-138","Klasztor","Pomerania","82","Powiat bytowski","2201","Lipnica","220105","53.9541","17.2848",""],"77-139":["PL","77-139","Brzezie\u0144ski M\u0142yn","Pomerania","82","Powiat bytowski","2201","Lipnica","220105","54.0072","17.2569",""],"77-140":["PL","77-140","R\u00f3\u017cki","Pomerania","82","Powiat bytowski","2201","Gmina Ko\u0142czyg\u0142owy","220104","54.2758","17.3273",""],"77-141":["PL","77-141","Osieki","Pomerania","82","Powiat bytowski","2201","Borzytuchom","220101","54.2265","17.4013",""],"77-142":["PL","77-142","K\u0142\u0105czno","Pomerania","82","Powiat bytowski","2201","Studzienice","220108","54.0727","17.5318",""],"77-143":["PL","77-143","Studzienice","Pomerania","82","Powiat bytowski","2201","Studzienice","220108","54.0904","17.5727","4"],"77-200":["PL","77-200","Turowo","Pomerania","82","Powiat bytowski","2201","Miastko","220106","54.0927","17.1683","4"],"77-203":["PL","77-203","Cisy","Pomerania","82","Powiat bytowski","2201","Miastko","220106","54.066","16.9809",""],"77-205":["PL","77-205","Po\u017cyczki","Pomerania","82","Powiat bytowski","2201","Miastko","220106","54.102","17.144",""],"77-206":["PL","77-206","Zagony","Pomerania","82","Powiat bytowski","2201","Tuchomie","220110","54.1145","17.2643","4"],"77-207":["PL","77-207","Borzykowo","Pomerania","82","Powiat bytowski","2201","Miastko","220106","54.0344","17.16",""],"77-211":["PL","77-211","\u0141\u0105ko\u0107","Pomerania","82","Powiat bytowski","2201","Miastko","220106","53.9285","16.9086",""],"77-222":["PL","77-222","Je\u017cewsko","Pomerania","82","Powiat bytowski","2201","Miastko","220106","54.0966","16.8751",""],"77-235":["PL","77-235","Toczek","Pomerania","82","Powiat bytowski","2201","Gmina Trzebielino","220109","54.2325","17.0668",""],"77-220":["PL","77-220","\u017bukowo","Pomerania","82","Powiat cz\u0142uchowski","2203","Gmina Kocza\u0142a","220305","53.855","17.0485",""],"77-300":["PL","77-300","Krery","Pomerania","82","Powiat cz\u0142uchowski","2203","Cz\u0142uch\u00f3w","220303","53.7073","17.4273",""],"77-304":["PL","77-304","Zalesie","Pomerania","82","Powiat cz\u0142uchowski","2203","Gmina Rzeczenica","220307","53.7177","17.098",""],"77-310":["PL","77-310","Grzymis\u0142aw","Pomerania","82","Powiat cz\u0142uchowski","2203","Gmina Debrzno","220304","53.5512","17.2035",""],"77-320":["PL","77-320","\u017bo\u0142na","Pomerania","82","Powiat cz\u0142uchowski","2203","Gmina Przechlewo","220306","53.9061","17.2398",""],"77-330":["PL","77-330","L\u0119dyczek Drugi","Pomerania","82","Powiat cz\u0142uchowski","2203","Gmina Czarne","220302","53.585","16.998",""],"77-230":["PL","77-230","Przyjezierze","Pomerania","82","Powiat s\u0142upski","2212","K\u0119pice","221205","54.1829","16.9239",""],"77-400":["PL","77-400","\u0141opienko","Greater Poland","86","Powiat z\u0142otowski","3031","Z\u0142ot\u00f3w","303108","53.3854","16.9974",""],"77-411":["PL","77-411","Stara Wi\u015bniewka","Greater Poland","86","Powiat z\u0142otowski","3031","Zakrzewo","303107","53.4508","17.0859","4"],"77-416":["PL","77-416","Tarn\u00f3wka Wybudowanie","Greater Poland","86","Powiat z\u0142otowski","3031","Tarn\u00f3wka","303106","53.3459","16.8758",""],"77-420":["PL","77-420","Bator\u00f3wko","Greater Poland","86","Powiat z\u0142otowski","3031","Lipka","303104","53.4828","17.3025",""],"77-424":["PL","77-424","Dro\u017cyska \u015arednie","Greater Poland","86","Powiat z\u0142otowski","3031","Zakrzewo","303107","53.3747","17.1282",""],"77-430":["PL","77-430","\u0141o\u0144sko","Greater Poland","86","Powiat z\u0142otowski","3031","Gmina Krajenka","303103","53.3139","17.0076",""],"77-470":["PL","77-470","Zalesie","Greater Poland","86","Powiat z\u0142otowski","3031","Z\u0142ot\u00f3w","303108","53.3599","16.9506","4"],"77-836":["PL","77-836","Koszalin","West Pomerania","87","Koszalin","3261","Koszalin","326101","54.1822","16.1763","4"],"77-499":["PL","77-499","Szczecin","West Pomerania","87","Szczecin","3262","Szczecin","326201","53.476","14.5118",""],"77-776":["PL","77-776","Szczecin","West Pomerania","87","Szczecin","3262","Szczecin","326201","53.3731","14.637",""]}