{"78-100":["PL","78-100","Bogucino","West Pomerania","87","Powiat ko\u0142obrzeski","3208","Ko\u0142obrzeg","320804","54.1201","15.6244","6"],"78-200":["PL","78-200","Nasutowo","West Pomerania","87","Powiat bia\u0142ogardzki","3201","Bia\u0142ogard","320102","53.981","15.8623","6"],"78-220":["PL","78-220","We\u0142dk\u00f3wko","West Pomerania","87","Powiat bia\u0142ogardzki","3201","Gmina Tychowo","320104","53.9783","16.3609","6"],"78-230":["PL","78-230","Go\u015bcinko","West Pomerania","87","Powiat bia\u0142ogardzki","3201","Gmina Karlino","320103","53.992","15.7404","6"],"78-445":["PL","78-445","Czochry\u0144","West Pomerania","87","Powiat szczecinecki","3215","Gmina Borne Sulinowo","321504","53.5338","16.4679","6"],"78-500":["PL","78-500","Suliszewo","West Pomerania","87","Powiat drawski","3203","Gmina Drawsko Pomorskie","320302","53.5232","15.8904","6"],"78-506":["PL","78-506","Drze\u0144sko","West Pomerania","87","Powiat drawski","3203","Gmina Ostrowice","320304","53.5775","16.0045","6"],"78-520":["PL","78-520","Darskowo","West Pomerania","87","Powiat drawski","3203","Gmina Z\u0142ocieniec","320306","53.5435","15.9562","6"],"78-523":["PL","78-523","Bolegorzyn","West Pomerania","87","Powiat drawski","3203","Gmina Ostrowice","320304","53.6589","16.1543","6"],"78-530":["PL","78-530","Bonin","West Pomerania","87","Powiat drawski","3203","Wierzchowo","320305","53.4791","16.0235","6"],"78-531":["PL","78-531","So\u015bnica","West Pomerania","87","Powiat drawski","3203","Wierzchowo","320305","53.4338","16.2028","6"],"78-540":["PL","78-540","Jaworze","West Pomerania","87","Powiat drawski","3203","Kalisz Pomorski","320303","53.3168","15.6903","6"],"78-550":["PL","78-550","We\u0142nica","West Pomerania","87","Powiat drawski","3203","Gmina Czaplinek","320301","53.5476","16.2598","6"],"78-551":["PL","78-551","Rzepowo","West Pomerania","87","Powiat drawski","3203","Gmina Czaplinek","320301","53.5934","16.0962","6"],"78-552":["PL","78-552","Kluczewo","West Pomerania","87","Powiat drawski","3203","Gmina Czaplinek","320301","53.6515","16.1866","6"],"78-553":["PL","78-553","Byszkowo","West Pomerania","87","Powiat drawski","3203","Gmina Czaplinek","320301","53.4946","16.294","6"],"78-102":["PL","78-102","Ko\u0142obrzeg","West Pomerania","87","Powiat ko\u0142obrzeski","3208","Ko\u0142obrzeg","320801","54.162","15.5507","6"],"78-103":["PL","78-103","Ko\u0142obrzeg","West Pomerania","87","Powiat ko\u0142obrzeski","3208","Ko\u0142obrzeg","320801","54.1842","15.5728","6"],"78-104":["PL","78-104","Ko\u0142obrzeg","West Pomerania","87","Powiat ko\u0142obrzeski","3208","Ko\u0142obrzeg","320801","54.1855","15.5548","6"],"78-107":["PL","78-107","Ko\u0142obrzeg","West Pomerania","87","Powiat ko\u0142obrzeski","3208","Ko\u0142obrzeg","320801","54.1708","15.5715","6"],"78-111":["PL","78-111","Olszyna","West Pomerania","87","Powiat ko\u0142obrzeski","3208","Gmina Ustronie Morskie","320807","54.203","15.7346","6"],"78-113":["PL","78-113","G\u0105skowo","West Pomerania","87","Powiat ko\u0142obrzeski","3208","Gmina Dygowo","320802","54.1467","15.7707","6"],"78-114":["PL","78-114","Jazy","West Pomerania","87","Powiat ko\u0142obrzeski","3208","Gmina Dygowo","320802","54.1246","15.7844","6"],"78-120":["PL","78-120","Jarogniew","West Pomerania","87","Powiat ko\u0142obrzeski","3208","Gmina Go\u015bcino","320803","54.0672","15.6423","6"],"78-122":["PL","78-122","Paprocie","West Pomerania","87","Powiat ko\u0142obrzeski","3208","Gmina Siemy\u015bl","320806","54.0776","15.4806",""],"78-123":["PL","78-123","\u015awiecie Ko\u0142obrzeskie","West Pomerania","87","Powiat ko\u0142obrzeski","3208","Gmina Siemy\u015bl","320806","54.0309","15.4607","6"],"78-125":["PL","78-125","Rzesznik\u00f3wko","West Pomerania","87","Powiat ko\u0142obrzeski","3208","Gmina Ryma\u0144","320805","53.9374","15.4732","6"],"78-131":["PL","78-131","D\u017awirzyno","West Pomerania","87","Powiat ko\u0142obrzeski","3208","Ko\u0142obrzeg","320804","54.1563","15.4132","6"],"78-132":["PL","78-132","Korzy\u015bcienko","West Pomerania","87","Powiat ko\u0142obrzeski","3208","Ko\u0142obrzeg","320804","54.1597","15.5195","6"],"78-133":["PL","78-133","Bogus\u0142awiec","West Pomerania","87","Powiat ko\u0142obrzeski","3208","Ko\u0142obrzeg","320804","54.0882","15.4673","6"],"78-400":["PL","78-400","Szczecin","West Pomerania","87","Szczecin","3262","Szczecin","326201","53.4297","14.4856","6"],"78-405":["PL","78-405","Spore","West Pomerania","87","Powiat szczecinecki","3215","Szczecinek","321506","53.8013","16.6888","6"],"78-407":["PL","78-407","Jelenino","West Pomerania","87","Powiat szczecinecki","3215","Szczecinek","321506","53.6517","16.6343","6"],"78-411":["PL","78-411","Spore","West Pomerania","87","Powiat szczecinecki","3215","Szczecinek","321506","53.801","16.6991","6"],"78-421":["PL","78-421","Drzonowo","West Pomerania","87","Powiat szczecinecki","3215","Gmina Bia\u0142y B\u00f3r","321503","53.8122","16.8486","6"],"78-422":["PL","78-422","Wielis\u0142awice","West Pomerania","87","Powiat szczecinecki","3215","Szczecinek","321506","53.7128","16.8188","6"],"78-425":["PL","78-425","Bagniewko","West Pomerania","87","Powiat szczecinecki","3215","Gmina Bia\u0142y B\u00f3r","321503","53.9806","16.8446","6"],"78-426":["PL","78-426","Ko\u0142tki","West Pomerania","87","Powiat szczecinecki","3215","Gmina Bia\u0142y B\u00f3r","321503","53.9566","16.8498","6"],"78-446":["PL","78-446","Jelonek","West Pomerania","87","Powiat szczecinecki","3215","Gmina Borne Sulinowo","321504","53.6185","16.6166","6"],"78-449":["PL","78-449","P\u0142ytnica","West Pomerania","87","Powiat szczecinecki","3215","Gmina Borne Sulinowo","321504","53.5915","16.6566","6"],"78-450":["PL","78-450","Szczecin","West Pomerania","87","Szczecin","3262","Szczecin","326201","53.4182","14.4834","6"],"78-451":["PL","78-451","Iwin","West Pomerania","87","Powiat szczecinecki","3215","Grzmi\u0105ca","321505","53.7961","16.5197","6"],"78-452":["PL","78-452","Krosino","West Pomerania","87","Powiat szczecinecki","3215","Grzmi\u0105ca","321505","53.842","16.3061","6"],"78-460":["PL","78-460","Uradz","West Pomerania","87","Powiat szczecinecki","3215","Gmina Barwice","321502","53.6792","16.3109","6"],"78-300":["PL","78-300","\u015awidwinek","West Pomerania","87","Powiat \u015bwidwi\u0144ski","3216","\u015awidwin","321606","53.762","15.7997","6"],"78-311":["PL","78-311","Blizno","West Pomerania","87","Powiat \u015bwidwi\u0144ski","3216","\u015awidwin","321606","53.7754","15.6062","6"],"78-312":["PL","78-312","Berkanowo","West Pomerania","87","Powiat \u015bwidwi\u0144ski","3216","\u015awidwin","321606","53.8267","15.5875","6"],"78-314":["PL","78-314","Mi\u0119dzyrzecko","West Pomerania","87","Powiat \u015bwidwi\u0144ski","3216","Gmina S\u0142awoborze","321605","53.8543","15.5579","6"],"78-316":["PL","78-316","Mulite","West Pomerania","87","Powiat \u015bwidwi\u0144ski","3216","Gmina Brze\u017cno","321602","53.718","15.8286","6"],"78-320":["PL","78-320","\u017bo\u0142\u0119dno","West Pomerania","87","Powiat \u015bwidwi\u0144ski","3216","Gmina Po\u0142czyn-Zdr\u00f3j","321603","53.7819","15.9844","6"],"78-324":["PL","78-324","Bierzwnica","West Pomerania","87","Powiat \u015bwidwi\u0144ski","3216","\u015awidwin","321606","53.7205","15.913","6"],"78-331":["PL","78-331","D\u0105br\u00f3wka","West Pomerania","87","Powiat \u015bwidwi\u0144ski","3216","Gmina R\u0105bino","321604","53.8576","15.8946","6"],"78-332":["PL","78-332","Do\u0142gan\u00f3w","West Pomerania","87","Powiat \u015bwidwi\u0144ski","3216","Gmina R\u0105bino","321604","53.8826","15.8131","4"],"78-600":["PL","78-600","Czapla","West Pomerania","87","Powiat wa\u0142ecki","3217","Wa\u0142cz","321705","53.2694","16.6051","6"],"78-607":["PL","78-607","Laski Wa\u0142eckie","West Pomerania","87","Powiat wa\u0142ecki","3217","Wa\u0142cz","321705","53.3641","16.2633","6"],"78-609":["PL","78-609","Karsib\u00f3r","West Pomerania","87","Powiat wa\u0142ecki","3217","Wa\u0142cz","321705","53.3513","16.3975","6"],"78-611":["PL","78-611","Szwecja","West Pomerania","87","Powiat wa\u0142ecki","3217","Wa\u0142cz","321705","53.3469","16.572","6"],"78-627":["PL","78-627","R\u00f3\u017cewo","West Pomerania","87","Powiat wa\u0142ecki","3217","Wa\u0142cz","321705","53.1973","16.4958","6"],"78-630":["PL","78-630","Drzonowo","West Pomerania","87","Powiat wa\u0142ecki","3217","Cz\u0142opa","321702","53.0446","16.1746","6"],"78-640":["PL","78-640","M\u0105czno","West Pomerania","87","Powiat wa\u0142ecki","3217","Gmina Tuczno","321704","53.2313","16.2423","6"],"78-641":["PL","78-641","Ponikiew","West Pomerania","87","Powiat wa\u0142ecki","3217","Gmina Tuczno","321704","53.2801","16.0894","6"],"78-642":["PL","78-642","Nakielno","West Pomerania","87","Powiat wa\u0142ecki","3217","Wa\u0142cz","321705","53.2637","16.3038","6"],"78-650":["PL","78-650","Pr\u00f3chnowo","West Pomerania","87","Powiat wa\u0142ecki","3217","Gmina Miros\u0142awiec","321703","53.3117","16.2396","6"],"78-813":["PL","78-813","Koszalin","West Pomerania","87","Koszalin","3261","Koszalin","326101","54.1506","16.2088","6"],"78-843":["PL","78-843","Szczecin","West Pomerania","87","Szczecin","3262","Szczecin","326201","53.4048","14.687","6"],"78-884":["PL","78-884","Szczecin","West Pomerania","87","Szczecin","3262","Szczecin","326201","53.3889","14.7716","6"]}